[{"fileLocalURL":"asset/audio","type":"file","isOpen":true,"isDirectory":true,"numChildren":3,"label":"audio","size":0},{"fileLocalURL":"asset/audio/bgm","type":"file","isOpen":true,"isDirectory":true,"numChildren":0,"label":"bgm","size":0},{"fileLocalURL":"asset/audio/bgs","type":"file","isOpen":true,"isDirectory":true,"numChildren":0,"label":"bgs","size":0},{"fileLocalURL":"asset/audio/se","type":"file","isOpen":true,"isDirectory":true,"numChildren":0,"label":"se","size":0},{"fileLocalURL":"asset/image","type":"file","isOpen":true,"isDirectory":true,"numChildren":5,"label":"image","size":0},{"fileLocalURL":"asset/image/animation","type":"file","isOpen":true,"isDirectory":true,"numChildren":1,"label":"animation","size":0},{"fileLocalURL":"asset/image/animation/particle","type":"file","isOpen":true,"isDirectory":true,"numChildren":0,"label":"particle","size":0},{"fileLocalURL":"asset/image/avatar","type":"file","isOpen":true,"isDirectory":true,"numChildren":1,"label":"avatar","size":0},{"fileLocalURL":"asset/image/avatar/NekoHead1.png","type":"image/png","isOpen":true,"isDirectory":false,"numChildren":0,"label":"NekoHead1.png","size":3087},{"fileLocalURL":"asset/image/picture","type":"file","isOpen":true,"isDirectory":true,"numChildren":3,"label":"picture","size":0},{"fileLocalURL":"asset/image/picture/face","type":"file","isOpen":true,"isDirectory":true,"numChildren":0,"label":"face","size":0},{"fileLocalURL":"asset/image/picture/control","type":"file","isOpen":true,"isDirectory":true,"numChildren":27,"label":"control","size":0},{"fileLocalURL":"asset/image/picture/control/btn_click.png","type":"image/png","isOpen":true,"isDirectory":false,"numChildren":0,"label":"btn_click.png","size":615},{"fileLocalURL":"asset/image/picture/control/btn_normal.png","type":"image/png","isOpen":true,"isDirectory":false,"numChildren":0,"label":"btn_normal.png","size":612},{"fileLocalURL":"asset/image/picture/control/btn_over.png","type":"image/png","isOpen":true,"isDirectory":false,"numChildren":0,"label":"btn_over.png","size":623},{"fileLocalURL":"asset/image/picture/control/check_selected.png","type":"image/png","isOpen":true,"isDirectory":false,"numChildren":0,"label":"check_selected.png","size":125},{"fileLocalURL":"asset/image/picture/control/check_unselected.png","type":"image/png","isOpen":true,"isDirectory":false,"numChildren":0,"label":"check_unselected.png","size":111},{"fileLocalURL":"asset/image/picture/control/slider_bg.png","type":"image/png","isOpen":true,"isDirectory":false,"numChildren":0,"label":"slider_bg.png","size":119},{"fileLocalURL":"asset/image/picture/control/slider_bgfill.png","type":"image/png","isOpen":true,"isDirectory":false,"numChildren":0,"label":"slider_bgfill.png","size":2831},{"fileLocalURL":"asset/image/picture/control/slider_block.png","type":"image/png","isOpen":true,"isDirectory":false,"numChildren":0,"label":"slider_block.png","size":368},{"fileLocalURL":"asset/image/picture/control/tab_selected.png","type":"image/png","isOpen":true,"isDirectory":false,"numChildren":0,"label":"tab_selected.png","size":188},{"fileLocalURL":"asset/image/picture/control/tab_unselected.png","type":"image/png","isOpen":true,"isDirectory":false,"numChildren":0,"label":"tab_unselected.png","size":188},{"fileLocalURL":"asset/image/picture/control/dialogSelect.png","type":"image/png","isOpen":true,"isDirectory":false,"numChildren":0,"label":"dialogSelect.png","size":2862},{"fileLocalURL":"asset/image/picture/control/hscroll_bar.png","type":"image/png","isOpen":true,"isDirectory":false,"numChildren":0,"label":"hscroll_bar.png","size":1790},{"fileLocalURL":"asset/image/picture/control/hscroll_bg.png","type":"image/png","isOpen":true,"isDirectory":false,"numChildren":0,"label":"hscroll_bg.png","size":1910},{"fileLocalURL":"asset/image/picture/control/uibitmap.png","type":"image/png","isOpen":true,"isDirectory":false,"numChildren":0,"label":"uibitmap.png","size":3352},{"fileLocalURL":"asset/image/picture/control/uicombobox.png","type":"image/png","isOpen":true,"isDirectory":false,"numChildren":0,"label":"uicombobox.png","size":188},{"fileLocalURL":"asset/image/picture/control/uicomboboxbg.png","type":"image/png","isOpen":true,"isDirectory":false,"numChildren":0,"label":"uicomboboxbg.png","size":161},{"fileLocalURL":"asset/image/picture/control/uicomboboxslider.png","type":"image/png","isOpen":true,"isDirectory":false,"numChildren":0,"label":"uicomboboxslider.png","size":2862},{"fileLocalURL":"asset/image/picture/control/uilistover.png","type":"image/png","isOpen":true,"isDirectory":false,"numChildren":0,"label":"uilistover.png","size":161},{"fileLocalURL":"asset/image/picture/control/uilistselect.png","type":"image/png","isOpen":true,"isDirectory":false,"numChildren":0,"label":"uilistselect.png","size":2862},{"fileLocalURL":"asset/image/picture/control/vscroll_bar.png","type":"image/png","isOpen":true,"isDirectory":false,"numChildren":0,"label":"vscroll_bar.png","size":259},{"fileLocalURL":"asset/image/picture/control/vscroll_bg.png","type":"image/png","isOpen":true,"isDirectory":false,"numChildren":0,"label":"vscroll_bg.png","size":1724},{"fileLocalURL":"asset/image/picture/control/cartoonDialog.png","type":"image/png","isOpen":true,"isDirectory":false,"numChildren":0,"label":"cartoonDialog.png","size":1641},{"fileLocalURL":"asset/image/picture/control/dialogBg.png","type":"image/png","isOpen":true,"isDirectory":false,"numChildren":0,"label":"dialogBg.png","size":2959},{"fileLocalURL":"asset/image/picture/control/dialogNormal.png","type":"image/png","isOpen":true,"isDirectory":false,"numChildren":0,"label":"dialogNormal.png","size":1860},{"fileLocalURL":"asset/image/picture/control/dialogOpDown.png","type":"image/png","isOpen":true,"isDirectory":false,"numChildren":0,"label":"dialogOpDown.png","size":1909},{"fileLocalURL":"asset/image/picture/control/dialogOpOver.png","type":"image/png","isOpen":true,"isDirectory":false,"numChildren":0,"label":"dialogOpOver.png","size":1756},{"fileLocalURL":"asset/image/picture/control/point.png","type":"image/png","isOpen":true,"isDirectory":false,"numChildren":0,"label":"point.png","size":100},{"fileLocalURL":"asset/image/picture/ian_plug","type":"file","isOpen":true,"isDirectory":true,"numChildren":1,"label":"ian_plug","size":0},{"fileLocalURL":"asset/image/picture/ian_plug/flappyBird","type":"file","isOpen":true,"isDirectory":true,"numChildren":0,"label":"flappyBird","size":0},{"fileLocalURL":"asset/image/scene","type":"file","isOpen":true,"isDirectory":true,"numChildren":1,"label":"scene","size":0},{"fileLocalURL":"asset/image/scene/fog","type":"file","isOpen":true,"isDirectory":true,"numChildren":0,"label":"fog","size":0},{"fileLocalURL":"asset/image/tile","type":"file","isOpen":true,"isDirectory":true,"numChildren":0,"label":"tile","size":0},{"fileLocalURL":"asset/json","type":"file","isOpen":false,"isDirectory":true,"numChildren":10,"label":"json","size":0},{"fileLocalURL":"asset/json/animation","type":"file","isOpen":false,"isDirectory":true,"numChildren":3,"label":"animation","size":0},{"fileLocalURL":"asset/json/animation/animationList.json","type":"file","isOpen":true,"isDirectory":false,"numChildren":0,"label":"animationList.json","size":336},{"fileLocalURL":"asset/json/animation/animationSignalList.json","type":"file","isOpen":true,"isDirectory":false,"numChildren":0,"label":"animationSignalList.json","size":144},{"fileLocalURL":"asset/json/animation/data","type":"file","isOpen":true,"isDirectory":true,"numChildren":10,"label":"data","size":0},{"fileLocalURL":"asset/json/animation/data/ani1.json","type":"file","isOpen":true,"isDirectory":false,"numChildren":0,"label":"ani1.json","size":6797},{"fileLocalURL":"asset/json/animation/data/ani10.json","type":"file","isOpen":true,"isDirectory":false,"numChildren":0,"label":"ani10.json","size":159},{"fileLocalURL":"asset/json/animation/data/ani2.json","type":"file","isOpen":true,"isDirectory":false,"numChildren":0,"label":"ani2.json","size":6148},{"fileLocalURL":"asset/json/animation/data/ani3.json","type":"file","isOpen":true,"isDirectory":false,"numChildren":0,"label":"ani3.json","size":6689},{"fileLocalURL":"asset/json/animation/data/ani4.json","type":"file","isOpen":true,"isDirectory":false,"numChildren":0,"label":"ani4.json","size":4246},{"fileLocalURL":"asset/json/animation/data/ani5.json","type":"file","isOpen":true,"isDirectory":false,"numChildren":0,"label":"ani5.json","size":2179},{"fileLocalURL":"asset/json/animation/data/ani6.json","type":"file","isOpen":true,"isDirectory":false,"numChildren":0,"label":"ani6.json","size":5447},{"fileLocalURL":"asset/json/animation/data/ani7.json","type":"file","isOpen":true,"isDirectory":false,"numChildren":0,"label":"ani7.json","size":158},{"fileLocalURL":"asset/json/animation/data/ani8.json","type":"file","isOpen":true,"isDirectory":false,"numChildren":0,"label":"ani8.json","size":158},{"fileLocalURL":"asset/json/animation/data/ani9.json","type":"file","isOpen":true,"isDirectory":false,"numChildren":0,"label":"ani9.json","size":158},{"fileLocalURL":"asset/json/avatar","type":"file","isOpen":false,"isDirectory":true,"numChildren":4,"label":"avatar","size":0},{"fileLocalURL":"asset/json/avatar/avatarActList.json","type":"file","isOpen":true,"isDirectory":false,"numChildren":0,"label":"avatarActList.json","size":144},{"fileLocalURL":"asset/json/avatar/avatarList.json","type":"file","isOpen":true,"isDirectory":false,"numChildren":0,"label":"avatarList.json","size":1813},{"fileLocalURL":"asset/json/avatar/avatarRefObjList.json","type":"file","isOpen":true,"isDirectory":false,"numChildren":0,"label":"avatarRefObjList.json","size":456},{"fileLocalURL":"asset/json/avatar/data","type":"file","isOpen":true,"isDirectory":true,"numChildren":63,"label":"data","size":0},{"fileLocalURL":"asset/json/avatar/data/avatar0.json","type":"file","isOpen":true,"isDirectory":false,"numChildren":0,"label":"avatar0.json","size":1486},{"fileLocalURL":"asset/json/avatar/data/avatar1.json","type":"file","isOpen":true,"isDirectory":false,"numChildren":0,"label":"avatar1.json","size":40977},{"fileLocalURL":"asset/json/avatar/data/avatar10.json","type":"file","isOpen":true,"isDirectory":false,"numChildren":0,"label":"avatar10.json","size":65236},{"fileLocalURL":"asset/json/avatar/data/avatar1001.json","type":"file","isOpen":true,"isDirectory":false,"numChildren":0,"label":"avatar1001.json","size":10665},{"fileLocalURL":"asset/json/avatar/data/avatar1002.json","type":"file","isOpen":true,"isDirectory":false,"numChildren":0,"label":"avatar1002.json","size":10666},{"fileLocalURL":"asset/json/avatar/data/avatar1003.json","type":"file","isOpen":true,"isDirectory":false,"numChildren":0,"label":"avatar1003.json","size":10656},{"fileLocalURL":"asset/json/avatar/data/avatar1004.json","type":"file","isOpen":true,"isDirectory":false,"numChildren":0,"label":"avatar1004.json","size":10656},{"fileLocalURL":"asset/json/avatar/data/avatar1005.json","type":"file","isOpen":true,"isDirectory":false,"numChildren":0,"label":"avatar1005.json","size":10641},{"fileLocalURL":"asset/json/avatar/data/avatar1006.json","type":"file","isOpen":true,"isDirectory":false,"numChildren":0,"label":"avatar1006.json","size":10641},{"fileLocalURL":"asset/json/avatar/data/avatar1007.json","type":"file","isOpen":true,"isDirectory":false,"numChildren":0,"label":"avatar1007.json","size":10641},{"fileLocalURL":"asset/json/avatar/data/avatar1008.json","type":"file","isOpen":true,"isDirectory":false,"numChildren":0,"label":"avatar1008.json","size":10641},{"fileLocalURL":"asset/json/avatar/data/avatar1009.json","type":"file","isOpen":true,"isDirectory":false,"numChildren":0,"label":"avatar1009.json","size":10641},{"fileLocalURL":"asset/json/avatar/data/avatar1010.json","type":"file","isOpen":true,"isDirectory":false,"numChildren":0,"label":"avatar1010.json","size":10641},{"fileLocalURL":"asset/json/avatar/data/avatar1011.json","type":"file","isOpen":true,"isDirectory":false,"numChildren":0,"label":"avatar1011.json","size":10644},{"fileLocalURL":"asset/json/avatar/data/avatar1012.json","type":"file","isOpen":true,"isDirectory":false,"numChildren":0,"label":"avatar1012.json","size":10650},{"fileLocalURL":"asset/json/avatar/data/avatar1013.json","type":"file","isOpen":true,"isDirectory":false,"numChildren":0,"label":"avatar1013.json","size":10650},{"fileLocalURL":"asset/json/avatar/data/avatar1014.json","type":"file","isOpen":true,"isDirectory":false,"numChildren":0,"label":"avatar1014.json","size":10641},{"fileLocalURL":"asset/json/avatar/data/avatar1015.json","type":"file","isOpen":true,"isDirectory":false,"numChildren":0,"label":"avatar1015.json","size":10641},{"fileLocalURL":"asset/json/avatar/data/avatar1016.json","type":"file","isOpen":true,"isDirectory":false,"numChildren":0,"label":"avatar1016.json","size":10641},{"fileLocalURL":"asset/json/avatar/data/avatar1017.json","type":"file","isOpen":true,"isDirectory":false,"numChildren":0,"label":"avatar1017.json","size":10641},{"fileLocalURL":"asset/json/avatar/data/avatar1018.json","type":"file","isOpen":true,"isDirectory":false,"numChildren":0,"label":"avatar1018.json","size":10688},{"fileLocalURL":"asset/json/avatar/data/avatar1019.json","type":"file","isOpen":true,"isDirectory":false,"numChildren":0,"label":"avatar1019.json","size":10641},{"fileLocalURL":"asset/json/avatar/data/avatar1020.json","type":"file","isOpen":true,"isDirectory":false,"numChildren":0,"label":"avatar1020.json","size":10647},{"fileLocalURL":"asset/json/avatar/data/avatar1021.json","type":"file","isOpen":true,"isDirectory":false,"numChildren":0,"label":"avatar1021.json","size":10650},{"fileLocalURL":"asset/json/avatar/data/avatar1022.json","type":"file","isOpen":true,"isDirectory":false,"numChildren":0,"label":"avatar1022.json","size":10641},{"fileLocalURL":"asset/json/avatar/data/avatar1023.json","type":"file","isOpen":true,"isDirectory":false,"numChildren":0,"label":"avatar1023.json","size":10647},{"fileLocalURL":"asset/json/avatar/data/avatar1024.json","type":"file","isOpen":true,"isDirectory":false,"numChildren":0,"label":"avatar1024.json","size":10647},{"fileLocalURL":"asset/json/avatar/data/avatar1025.json","type":"file","isOpen":true,"isDirectory":false,"numChildren":0,"label":"avatar1025.json","size":10682},{"fileLocalURL":"asset/json/avatar/data/avatar1026.json","type":"file","isOpen":true,"isDirectory":false,"numChildren":0,"label":"avatar1026.json","size":10641},{"fileLocalURL":"asset/json/avatar/data/avatar1027.json","type":"file","isOpen":true,"isDirectory":false,"numChildren":0,"label":"avatar1027.json","size":10644},{"fileLocalURL":"asset/json/avatar/data/avatar1028.json","type":"file","isOpen":true,"isDirectory":false,"numChildren":0,"label":"avatar1028.json","size":10642},{"fileLocalURL":"asset/json/avatar/data/avatar1029.json","type":"file","isOpen":true,"isDirectory":false,"numChildren":0,"label":"avatar1029.json","size":413},{"fileLocalURL":"asset/json/avatar/data/avatar1030.json","type":"file","isOpen":true,"isDirectory":false,"numChildren":0,"label":"avatar1030.json","size":413},{"fileLocalURL":"asset/json/avatar/data/avatar11.json","type":"file","isOpen":true,"isDirectory":false,"numChildren":0,"label":"avatar11.json","size":65230},{"fileLocalURL":"asset/json/avatar/data/avatar12.json","type":"file","isOpen":true,"isDirectory":false,"numChildren":0,"label":"avatar12.json","size":65230},{"fileLocalURL":"asset/json/avatar/data/avatar13.json","type":"file","isOpen":true,"isDirectory":false,"numChildren":0,"label":"avatar13.json","size":65260},{"fileLocalURL":"asset/json/avatar/data/avatar14.json","type":"file","isOpen":true,"isDirectory":false,"numChildren":0,"label":"avatar14.json","size":65260},{"fileLocalURL":"asset/json/avatar/data/avatar15.json","type":"file","isOpen":true,"isDirectory":false,"numChildren":0,"label":"avatar15.json","size":65230},{"fileLocalURL":"asset/json/avatar/data/avatar16.json","type":"file","isOpen":true,"isDirectory":false,"numChildren":0,"label":"avatar16.json","size":65230},{"fileLocalURL":"asset/json/avatar/data/avatar17.json","type":"file","isOpen":true,"isDirectory":false,"numChildren":0,"label":"avatar17.json","size":65230},{"fileLocalURL":"asset/json/avatar/data/avatar18.json","type":"file","isOpen":true,"isDirectory":false,"numChildren":0,"label":"avatar18.json","size":65230},{"fileLocalURL":"asset/json/avatar/data/avatar19.json","type":"file","isOpen":true,"isDirectory":false,"numChildren":0,"label":"avatar19.json","size":65230},{"fileLocalURL":"asset/json/avatar/data/avatar2.json","type":"file","isOpen":true,"isDirectory":false,"numChildren":0,"label":"avatar2.json","size":65229},{"fileLocalURL":"asset/json/avatar/data/avatar20.json","type":"file","isOpen":true,"isDirectory":false,"numChildren":0,"label":"avatar20.json","size":65230},{"fileLocalURL":"asset/json/avatar/data/avatar2001.json","type":"file","isOpen":true,"isDirectory":false,"numChildren":0,"label":"avatar2001.json","size":413},{"fileLocalURL":"asset/json/avatar/data/avatar2002.json","type":"file","isOpen":true,"isDirectory":false,"numChildren":0,"label":"avatar2002.json","size":413},{"fileLocalURL":"asset/json/avatar/data/avatar21.json","type":"file","isOpen":true,"isDirectory":false,"numChildren":0,"label":"avatar21.json","size":65260},{"fileLocalURL":"asset/json/avatar/data/avatar22.json","type":"file","isOpen":true,"isDirectory":false,"numChildren":0,"label":"avatar22.json","size":65230},{"fileLocalURL":"asset/json/avatar/data/avatar23.json","type":"file","isOpen":true,"isDirectory":false,"numChildren":0,"label":"avatar23.json","size":411},{"fileLocalURL":"asset/json/avatar/data/avatar24.json","type":"file","isOpen":true,"isDirectory":false,"numChildren":0,"label":"avatar24.json","size":411},{"fileLocalURL":"asset/json/avatar/data/avatar25.json","type":"file","isOpen":true,"isDirectory":false,"numChildren":0,"label":"avatar25.json","size":411},{"fileLocalURL":"asset/json/avatar/data/avatar26.json","type":"file","isOpen":true,"isDirectory":false,"numChildren":0,"label":"avatar26.json","size":335},{"fileLocalURL":"asset/json/avatar/data/avatar27.json","type":"file","isOpen":true,"isDirectory":false,"numChildren":0,"label":"avatar27.json","size":335},{"fileLocalURL":"asset/json/avatar/data/avatar28.json","type":"file","isOpen":true,"isDirectory":false,"numChildren":0,"label":"avatar28.json","size":335},{"fileLocalURL":"asset/json/avatar/data/avatar29.json","type":"file","isOpen":true,"isDirectory":false,"numChildren":0,"label":"avatar29.json","size":335},{"fileLocalURL":"asset/json/avatar/data/avatar3.json","type":"file","isOpen":true,"isDirectory":false,"numChildren":0,"label":"avatar3.json","size":65235},{"fileLocalURL":"asset/json/avatar/data/avatar30.json","type":"file","isOpen":true,"isDirectory":false,"numChildren":0,"label":"avatar30.json","size":335},{"fileLocalURL":"asset/json/avatar/data/avatar4.json","type":"file","isOpen":true,"isDirectory":false,"numChildren":0,"label":"avatar4.json","size":65235},{"fileLocalURL":"asset/json/avatar/data/avatar5.json","type":"file","isOpen":true,"isDirectory":false,"numChildren":0,"label":"avatar5.json","size":65229},{"fileLocalURL":"asset/json/avatar/data/avatar6.json","type":"file","isOpen":true,"isDirectory":false,"numChildren":0,"label":"avatar6.json","size":65229},{"fileLocalURL":"asset/json/avatar/data/avatar7.json","type":"file","isOpen":true,"isDirectory":false,"numChildren":0,"label":"avatar7.json","size":65229},{"fileLocalURL":"asset/json/avatar/data/avatar8.json","type":"file","isOpen":true,"isDirectory":false,"numChildren":0,"label":"avatar8.json","size":65235},{"fileLocalURL":"asset/json/avatar/data/avatar9.json","type":"file","isOpen":true,"isDirectory":false,"numChildren":0,"label":"avatar9.json","size":65235},{"fileLocalURL":"asset/json/config.json","type":"file","isOpen":true,"isDirectory":false,"numChildren":0,"label":"config.json","size":468},{"fileLocalURL":"asset/json/custom","type":"file","isOpen":false,"isDirectory":true,"numChildren":10,"label":"custom","size":0},{"fileLocalURL":"asset/json/custom/customGameAttribute.json","type":"file","isOpen":true,"isDirectory":false,"numChildren":0,"label":"customGameAttribute.json","size":12561},{"fileLocalURL":"asset/json/custom/customModule","type":"file","isOpen":true,"isDirectory":true,"numChildren":6,"label":"customModule","size":0},{"fileLocalURL":"asset/json/custom/customModule/1","type":"file","isOpen":true,"isDirectory":true,"numChildren":4,"label":"1","size":0},{"fileLocalURL":"asset/json/custom/customModule/1/cm1.json","type":"file","isOpen":true,"isDirectory":false,"numChildren":0,"label":"cm1.json","size":485},{"fileLocalURL":"asset/json/custom/customModule/1/cm2.json","type":"file","isOpen":true,"isDirectory":false,"numChildren":0,"label":"cm2.json","size":511},{"fileLocalURL":"asset/json/custom/customModule/1/cm3.json","type":"file","isOpen":true,"isDirectory":false,"numChildren":0,"label":"cm3.json","size":511},{"fileLocalURL":"asset/json/custom/customModule/1/cm4.json","type":"file","isOpen":true,"isDirectory":false,"numChildren":0,"label":"cm4.json","size":1505},{"fileLocalURL":"asset/json/custom/customModule/2","type":"file","isOpen":true,"isDirectory":true,"numChildren":3,"label":"2","size":0},{"fileLocalURL":"asset/json/custom/customModule/2/cm1.json","type":"file","isOpen":true,"isDirectory":false,"numChildren":0,"label":"cm1.json","size":455},{"fileLocalURL":"asset/json/custom/customModule/2/cm2.json","type":"file","isOpen":true,"isDirectory":false,"numChildren":0,"label":"cm2.json","size":460},{"fileLocalURL":"asset/json/custom/customModule/2/cm3.json","type":"file","isOpen":true,"isDirectory":false,"numChildren":0,"label":"cm3.json","size":3113},{"fileLocalURL":"asset/json/custom/customModule/customModuleDataList1.json","type":"file","isOpen":true,"isDirectory":false,"numChildren":0,"label":"customModuleDataList1.json","size":153},{"fileLocalURL":"asset/json/custom/customModule/customModuleDataList2.json","type":"file","isOpen":true,"isDirectory":false,"numChildren":0,"label":"customModuleDataList2.json","size":131},{"fileLocalURL":"asset/json/custom/customModule/3","type":"file","isOpen":true,"isDirectory":true,"numChildren":3,"label":"3","size":0},{"fileLocalURL":"asset/json/custom/customModule/3/cm1.json","type":"file","isOpen":true,"isDirectory":false,"numChildren":0,"label":"cm1.json","size":152},{"fileLocalURL":"asset/json/custom/customModule/3/cm2.json","type":"file","isOpen":true,"isDirectory":false,"numChildren":0,"label":"cm2.json","size":152},{"fileLocalURL":"asset/json/custom/customModule/3/cm3.json","type":"file","isOpen":true,"isDirectory":false,"numChildren":0,"label":"cm3.json","size":152},{"fileLocalURL":"asset/json/custom/customModule/customModuleDataList3.json","type":"file","isOpen":true,"isDirectory":false,"numChildren":0,"label":"customModuleDataList3.json","size":139},{"fileLocalURL":"asset/json/custom/customModuleList.json","type":"file","isOpen":true,"isDirectory":false,"numChildren":0,"label":"customModuleList.json","size":13959},{"fileLocalURL":"asset/json/custom/dataStructure.json","type":"file","isOpen":true,"isDirectory":false,"numChildren":0,"label":"dataStructure.json","size":26698},{"fileLocalURL":"asset/json/custom/customBehaviorType.json","type":"file","isOpen":true,"isDirectory":false,"numChildren":0,"label":"customBehaviorType.json","size":62531},{"fileLocalURL":"asset/json/custom/customCommandType.json","type":"file","isOpen":true,"isDirectory":false,"numChildren":0,"label":"customCommandType.json","size":58873},{"fileLocalURL":"asset/json/custom/customObjectEventType.json","type":"file","isOpen":true,"isDirectory":false,"numChildren":0,"label":"customObjectEventType.json","size":664},{"fileLocalURL":"asset/json/custom/customSceneEventType.json","type":"file","isOpen":true,"isDirectory":false,"numChildren":0,"label":"customSceneEventType.json","size":244},{"fileLocalURL":"asset/json/custom/customUIEventType.json","type":"file","isOpen":true,"isDirectory":false,"numChildren":0,"label":"customUIEventType.json","size":256},{"fileLocalURL":"asset/json/custom/customValueFunction.json","type":"file","isOpen":true,"isDirectory":false,"numChildren":0,"label":"customValueFunction.json","size":942},{"fileLocalURL":"asset/json/dialog","type":"file","isOpen":false,"isDirectory":true,"numChildren":2,"label":"dialog","size":0},{"fileLocalURL":"asset/json/dialog/data","type":"file","isOpen":true,"isDirectory":true,"numChildren":2,"label":"data","size":0},{"fileLocalURL":"asset/json/dialog/data/dialog1.json","type":"file","isOpen":true,"isDirectory":false,"numChildren":0,"label":"dialog1.json","size":1422},{"fileLocalURL":"asset/json/dialog/data/dialog2.json","type":"file","isOpen":true,"isDirectory":false,"numChildren":0,"label":"dialog2.json","size":1465},{"fileLocalURL":"asset/json/dialog/dialogList.json","type":"file","isOpen":true,"isDirectory":false,"numChildren":0,"label":"dialogList.json","size":58},{"fileLocalURL":"asset/json/scene","type":"file","isOpen":false,"isDirectory":true,"numChildren":6,"label":"scene","size":0},{"fileLocalURL":"asset/json/scene/data","type":"file","isOpen":true,"isDirectory":true,"numChildren":28,"label":"data","size":0},{"fileLocalURL":"asset/json/scene/data/scene1.json","type":"file","isOpen":true,"isDirectory":false,"numChildren":0,"label":"scene1.json","size":107075},{"fileLocalURL":"asset/json/scene/data/scene10.json","type":"file","isOpen":true,"isDirectory":false,"numChildren":0,"label":"scene10.json","size":17061},{"fileLocalURL":"asset/json/scene/data/scene11.json","type":"file","isOpen":true,"isDirectory":false,"numChildren":0,"label":"scene11.json","size":22848},{"fileLocalURL":"asset/json/scene/data/scene12.json","type":"file","isOpen":true,"isDirectory":false,"numChildren":0,"label":"scene12.json","size":2453},{"fileLocalURL":"asset/json/scene/data/scene13.json","type":"file","isOpen":true,"isDirectory":false,"numChildren":0,"label":"scene13.json","size":6275},{"fileLocalURL":"asset/json/scene/data/scene14.json","type":"file","isOpen":true,"isDirectory":false,"numChildren":0,"label":"scene14.json","size":2436},{"fileLocalURL":"asset/json/scene/data/scene15.json","type":"file","isOpen":true,"isDirectory":false,"numChildren":0,"label":"scene15.json","size":2447},{"fileLocalURL":"asset/json/scene/data/scene16.json","type":"file","isOpen":true,"isDirectory":false,"numChildren":0,"label":"scene16.json","size":2436},{"fileLocalURL":"asset/json/scene/data/scene17.json","type":"file","isOpen":true,"isDirectory":false,"numChildren":0,"label":"scene17.json","size":2436},{"fileLocalURL":"asset/json/scene/data/scene18.json","type":"file","isOpen":true,"isDirectory":false,"numChildren":0,"label":"scene18.json","size":27284},{"fileLocalURL":"asset/json/scene/data/scene2.json","type":"file","isOpen":true,"isDirectory":false,"numChildren":0,"label":"scene2.json","size":106412},{"fileLocalURL":"asset/json/scene/data/scene3.json","type":"file","isOpen":true,"isDirectory":false,"numChildren":0,"label":"scene3.json","size":2455},{"fileLocalURL":"asset/json/scene/data/scene4.json","type":"file","isOpen":true,"isDirectory":false,"numChildren":0,"label":"scene4.json","size":463832},{"fileLocalURL":"asset/json/scene/data/scene5.json","type":"file","isOpen":true,"isDirectory":false,"numChildren":0,"label":"scene5.json","size":2506},{"fileLocalURL":"asset/json/scene/data/scene6.json","type":"file","isOpen":true,"isDirectory":false,"numChildren":0,"label":"scene6.json","size":2506},{"fileLocalURL":"asset/json/scene/data/scene7.json","type":"file","isOpen":true,"isDirectory":false,"numChildren":0,"label":"scene7.json","size":2447},{"fileLocalURL":"asset/json/scene/data/scene8.json","type":"file","isOpen":true,"isDirectory":false,"numChildren":0,"label":"scene8.json","size":26509},{"fileLocalURL":"asset/json/scene/data/scene9.json","type":"file","isOpen":true,"isDirectory":false,"numChildren":0,"label":"scene9.json","size":17919},{"fileLocalURL":"asset/json/scene/data/scene19.json","type":"file","isOpen":true,"isDirectory":false,"numChildren":0,"label":"scene19.json","size":1441},{"fileLocalURL":"asset/json/scene/data/scene20.json","type":"file","isOpen":true,"isDirectory":false,"numChildren":0,"label":"scene20.json","size":2923},{"fileLocalURL":"asset/json/scene/data/scene21.json","type":"file","isOpen":true,"isDirectory":false,"numChildren":0,"label":"scene21.json","size":1778030},{"fileLocalURL":"asset/json/scene/data/scene22.json","type":"file","isOpen":true,"isDirectory":false,"numChildren":0,"label":"scene22.json","size":3222},{"fileLocalURL":"asset/json/scene/data/scene23.json","type":"file","isOpen":true,"isDirectory":false,"numChildren":0,"label":"scene23.json","size":7525},{"fileLocalURL":"asset/json/scene/data/scene24.json","type":"file","isOpen":true,"isDirectory":false,"numChildren":0,"label":"scene24.json","size":1471529},{"fileLocalURL":"asset/json/scene/data/scene25.json","type":"file","isOpen":true,"isDirectory":false,"numChildren":0,"label":"scene25.json","size":894486},{"fileLocalURL":"asset/json/scene/data/scene26.json","type":"file","isOpen":true,"isDirectory":false,"numChildren":0,"label":"scene26.json","size":368847},{"fileLocalURL":"asset/json/scene/data/scene27.json","type":"file","isOpen":true,"isDirectory":false,"numChildren":0,"label":"scene27.json","size":77898},{"fileLocalURL":"asset/json/scene/data/scene28.json","type":"file","isOpen":true,"isDirectory":false,"numChildren":0,"label":"scene28.json","size":83308},{"fileLocalURL":"asset/json/scene/model","type":"file","isOpen":true,"isDirectory":true,"numChildren":7,"label":"model","size":0},{"fileLocalURL":"asset/json/scene/model/som1.json","type":"file","isOpen":true,"isDirectory":false,"numChildren":0,"label":"som1.json","size":497},{"fileLocalURL":"asset/json/scene/model/som2.json","type":"file","isOpen":true,"isDirectory":false,"numChildren":0,"label":"som2.json","size":1673},{"fileLocalURL":"asset/json/scene/model/som3.json","type":"file","isOpen":true,"isDirectory":false,"numChildren":0,"label":"som3.json","size":403},{"fileLocalURL":"asset/json/scene/model/som4.json","type":"file","isOpen":true,"isDirectory":false,"numChildren":0,"label":"som4.json","size":133},{"fileLocalURL":"asset/json/scene/model/som5.json","type":"file","isOpen":true,"isDirectory":false,"numChildren":0,"label":"som5.json","size":133},{"fileLocalURL":"asset/json/scene/model/som6.json","type":"file","isOpen":true,"isDirectory":false,"numChildren":0,"label":"som6.json","size":166},{"fileLocalURL":"asset/json/scene/model/som7.json","type":"file","isOpen":true,"isDirectory":false,"numChildren":0,"label":"som7.json","size":60},{"fileLocalURL":"asset/json/scene/sceneList.json","type":"file","isOpen":true,"isDirectory":false,"numChildren":0,"label":"sceneList.json","size":612},{"fileLocalURL":"asset/json/scene/sceneObjectModelList.json","type":"file","isOpen":true,"isDirectory":false,"numChildren":0,"label":"sceneObjectModelList.json","size":116},{"fileLocalURL":"asset/json/scene/tile","type":"file","isOpen":true,"isDirectory":true,"numChildren":13,"label":"tile","size":0},{"fileLocalURL":"asset/json/scene/tile/tile1.json","type":"file","isOpen":true,"isDirectory":false,"numChildren":0,"label":"tile1.json","size":5331},{"fileLocalURL":"asset/json/scene/tile/tile10.json","type":"file","isOpen":true,"isDirectory":false,"numChildren":0,"label":"tile10.json","size":11099},{"fileLocalURL":"asset/json/scene/tile/tile11.json","type":"file","isOpen":true,"isDirectory":false,"numChildren":0,"label":"tile11.json","size":6913},{"fileLocalURL":"asset/json/scene/tile/tile12.json","type":"file","isOpen":true,"isDirectory":false,"numChildren":0,"label":"tile12.json","size":12035},{"fileLocalURL":"asset/json/scene/tile/tile2.json","type":"file","isOpen":true,"isDirectory":false,"numChildren":0,"label":"tile2.json","size":10513},{"fileLocalURL":"asset/json/scene/tile/tile3.json","type":"file","isOpen":true,"isDirectory":false,"numChildren":0,"label":"tile3.json","size":41459},{"fileLocalURL":"asset/json/scene/tile/tile4.json","type":"file","isOpen":true,"isDirectory":false,"numChildren":0,"label":"tile4.json","size":37847},{"fileLocalURL":"asset/json/scene/tile/tile5.json","type":"file","isOpen":true,"isDirectory":false,"numChildren":0,"label":"tile5.json","size":58632},{"fileLocalURL":"asset/json/scene/tile/tile6.json","type":"file","isOpen":true,"isDirectory":false,"numChildren":0,"label":"tile6.json","size":51553},{"fileLocalURL":"asset/json/scene/tile/tile7.json","type":"file","isOpen":true,"isDirectory":false,"numChildren":0,"label":"tile7.json","size":59685},{"fileLocalURL":"asset/json/scene/tile/tile8.json","type":"file","isOpen":true,"isDirectory":false,"numChildren":0,"label":"tile8.json","size":81584},{"fileLocalURL":"asset/json/scene/tile/tile9.json","type":"file","isOpen":true,"isDirectory":false,"numChildren":0,"label":"tile9.json","size":166817},{"fileLocalURL":"asset/json/scene/tile/tile13.json","type":"file","isOpen":true,"isDirectory":false,"numChildren":0,"label":"tile13.json","size":86},{"fileLocalURL":"asset/json/scene/tileList.json","type":"file","isOpen":true,"isDirectory":false,"numChildren":0,"label":"tileList.json","size":254},{"fileLocalURL":"asset/json/server","type":"file","isOpen":false,"isDirectory":true,"numChildren":5,"label":"server","size":0},{"fileLocalURL":"asset/json/server/command","type":"file","isOpen":true,"isDirectory":true,"numChildren":2,"label":"command","size":0},{"fileLocalURL":"asset/json/server/command/data","type":"file","isOpen":true,"isDirectory":true,"numChildren":17,"label":"data","size":0},{"fileLocalURL":"asset/json/server/command/data/ws1.json","type":"file","isOpen":true,"isDirectory":false,"numChildren":0,"label":"ws1.json","size":1114},{"fileLocalURL":"asset/json/server/command/data/ws10.json","type":"file","isOpen":true,"isDirectory":false,"numChildren":0,"label":"ws10.json","size":113},{"fileLocalURL":"asset/json/server/command/data/ws1001.json","type":"file","isOpen":true,"isDirectory":false,"numChildren":0,"label":"ws1001.json","size":115},{"fileLocalURL":"asset/json/server/command/data/ws1002.json","type":"file","isOpen":true,"isDirectory":false,"numChildren":0,"label":"ws1002.json","size":84},{"fileLocalURL":"asset/json/server/command/data/ws1003.json","type":"file","isOpen":true,"isDirectory":false,"numChildren":0,"label":"ws1003.json","size":83},{"fileLocalURL":"asset/json/server/command/data/ws1004.json","type":"file","isOpen":true,"isDirectory":false,"numChildren":0,"label":"ws1004.json","size":84},{"fileLocalURL":"asset/json/server/command/data/ws1005.json","type":"file","isOpen":true,"isDirectory":false,"numChildren":0,"label":"ws1005.json","size":84},{"fileLocalURL":"asset/json/server/command/data/ws2.json","type":"file","isOpen":true,"isDirectory":false,"numChildren":0,"label":"ws2.json","size":1025},{"fileLocalURL":"asset/json/server/command/data/ws2001.json","type":"file","isOpen":true,"isDirectory":false,"numChildren":0,"label":"ws2001.json","size":115},{"fileLocalURL":"asset/json/server/command/data/ws3.json","type":"file","isOpen":true,"isDirectory":false,"numChildren":0,"label":"ws3.json","size":1105},{"fileLocalURL":"asset/json/server/command/data/ws3001.json","type":"file","isOpen":true,"isDirectory":false,"numChildren":0,"label":"ws3001.json","size":115},{"fileLocalURL":"asset/json/server/command/data/ws4.json","type":"file","isOpen":true,"isDirectory":false,"numChildren":0,"label":"ws4.json","size":1016},{"fileLocalURL":"asset/json/server/command/data/ws5.json","type":"file","isOpen":true,"isDirectory":false,"numChildren":0,"label":"ws5.json","size":10179},{"fileLocalURL":"asset/json/server/command/data/ws6.json","type":"file","isOpen":true,"isDirectory":false,"numChildren":0,"label":"ws6.json","size":1484},{"fileLocalURL":"asset/json/server/command/data/ws7.json","type":"file","isOpen":true,"isDirectory":false,"numChildren":0,"label":"ws7.json","size":11845},{"fileLocalURL":"asset/json/server/command/data/ws8.json","type":"file","isOpen":true,"isDirectory":false,"numChildren":0,"label":"ws8.json","size":520},{"fileLocalURL":"asset/json/server/command/data/ws9.json","type":"file","isOpen":true,"isDirectory":false,"numChildren":0,"label":"ws9.json","size":112},{"fileLocalURL":"asset/json/server/command/worldCommand.json","type":"file","isOpen":true,"isDirectory":false,"numChildren":0,"label":"worldCommand.json","size":693},{"fileLocalURL":"asset/json/server/scene","type":"file","isOpen":true,"isDirectory":true,"numChildren":28,"label":"scene","size":0},{"fileLocalURL":"asset/json/server/scene/s1.json","type":"file","isOpen":true,"isDirectory":false,"numChildren":0,"label":"s1.json","size":6927},{"fileLocalURL":"asset/json/server/scene/s10.json","type":"file","isOpen":true,"isDirectory":false,"numChildren":0,"label":"s10.json","size":6358},{"fileLocalURL":"asset/json/server/scene/s11.json","type":"file","isOpen":true,"isDirectory":false,"numChildren":0,"label":"s11.json","size":2738},{"fileLocalURL":"asset/json/server/scene/s12.json","type":"file","isOpen":true,"isDirectory":false,"numChildren":0,"label":"s12.json","size":127},{"fileLocalURL":"asset/json/server/scene/s13.json","type":"file","isOpen":true,"isDirectory":false,"numChildren":0,"label":"s13.json","size":127},{"fileLocalURL":"asset/json/server/scene/s14.json","type":"file","isOpen":true,"isDirectory":false,"numChildren":0,"label":"s14.json","size":127},{"fileLocalURL":"asset/json/server/scene/s15.json","type":"file","isOpen":true,"isDirectory":false,"numChildren":0,"label":"s15.json","size":127},{"fileLocalURL":"asset/json/server/scene/s16.json","type":"file","isOpen":true,"isDirectory":false,"numChildren":0,"label":"s16.json","size":127},{"fileLocalURL":"asset/json/server/scene/s17.json","type":"file","isOpen":true,"isDirectory":false,"numChildren":0,"label":"s17.json","size":127},{"fileLocalURL":"asset/json/server/scene/s18.json","type":"file","isOpen":true,"isDirectory":false,"numChildren":0,"label":"s18.json","size":4073},{"fileLocalURL":"asset/json/server/scene/s19.json","type":"file","isOpen":true,"isDirectory":false,"numChildren":0,"label":"s19.json","size":32197},{"fileLocalURL":"asset/json/server/scene/s2.json","type":"file","isOpen":true,"isDirectory":false,"numChildren":0,"label":"s2.json","size":14524},{"fileLocalURL":"asset/json/server/scene/s20.json","type":"file","isOpen":true,"isDirectory":false,"numChildren":0,"label":"s20.json","size":320},{"fileLocalURL":"asset/json/server/scene/s21.json","type":"file","isOpen":true,"isDirectory":false,"numChildren":0,"label":"s21.json","size":27737},{"fileLocalURL":"asset/json/server/scene/s22.json","type":"file","isOpen":true,"isDirectory":false,"numChildren":0,"label":"s22.json","size":14475},{"fileLocalURL":"asset/json/server/scene/s3.json","type":"file","isOpen":true,"isDirectory":false,"numChildren":0,"label":"s3.json","size":17848},{"fileLocalURL":"asset/json/server/scene/s4.json","type":"file","isOpen":true,"isDirectory":false,"numChildren":0,"label":"s4.json","size":16012},{"fileLocalURL":"asset/json/server/scene/s5.json","type":"file","isOpen":true,"isDirectory":false,"numChildren":0,"label":"s5.json","size":126},{"fileLocalURL":"asset/json/server/scene/s6.json","type":"file","isOpen":true,"isDirectory":false,"numChildren":0,"label":"s6.json","size":356},{"fileLocalURL":"asset/json/server/scene/s7.json","type":"file","isOpen":true,"isDirectory":false,"numChildren":0,"label":"s7.json","size":598},{"fileLocalURL":"asset/json/server/scene/s8.json","type":"file","isOpen":true,"isDirectory":false,"numChildren":0,"label":"s8.json","size":68706},{"fileLocalURL":"asset/json/server/scene/s9.json","type":"file","isOpen":true,"isDirectory":false,"numChildren":0,"label":"s9.json","size":12735},{"fileLocalURL":"asset/json/server/scene/s23.json","type":"file","isOpen":true,"isDirectory":false,"numChildren":0,"label":"s23.json","size":149},{"fileLocalURL":"asset/json/server/scene/s24.json","type":"file","isOpen":true,"isDirectory":false,"numChildren":0,"label":"s24.json","size":20203},{"fileLocalURL":"asset/json/server/scene/s25.json","type":"file","isOpen":true,"isDirectory":false,"numChildren":0,"label":"s25.json","size":26618},{"fileLocalURL":"asset/json/server/scene/s26.json","type":"file","isOpen":true,"isDirectory":false,"numChildren":0,"label":"s26.json","size":20288},{"fileLocalURL":"asset/json/server/scene/s27.json","type":"file","isOpen":true,"isDirectory":false,"numChildren":0,"label":"s27.json","size":6899},{"fileLocalURL":"asset/json/server/scene/s28.json","type":"file","isOpen":true,"isDirectory":false,"numChildren":0,"label":"s28.json","size":14696},{"fileLocalURL":"asset/json/server/serverConfig.json","type":"file","isOpen":true,"isDirectory":false,"numChildren":0,"label":"serverConfig.json","size":2337},{"fileLocalURL":"asset/json/server/ui","type":"file","isOpen":true,"isDirectory":true,"numChildren":33,"label":"ui","size":0},{"fileLocalURL":"asset/json/server/ui/sui1.json","type":"file","isOpen":true,"isDirectory":false,"numChildren":0,"label":"sui1.json","size":862},{"fileLocalURL":"asset/json/server/ui/sui2.json","type":"file","isOpen":true,"isDirectory":false,"numChildren":0,"label":"sui2.json","size":1278},{"fileLocalURL":"asset/json/server/ui/sui3.json","type":"file","isOpen":true,"isDirectory":false,"numChildren":0,"label":"sui3.json","size":196},{"fileLocalURL":"asset/json/server/ui/sui4.json","type":"file","isOpen":true,"isDirectory":false,"numChildren":0,"label":"sui4.json","size":563},{"fileLocalURL":"asset/json/server/ui/sui10.json","type":"file","isOpen":true,"isDirectory":false,"numChildren":0,"label":"sui10.json","size":725},{"fileLocalURL":"asset/json/server/ui/sui1001.json","type":"file","isOpen":true,"isDirectory":false,"numChildren":0,"label":"sui1001.json","size":121},{"fileLocalURL":"asset/json/server/ui/sui11.json","type":"file","isOpen":true,"isDirectory":false,"numChildren":0,"label":"sui11.json","size":370},{"fileLocalURL":"asset/json/server/ui/sui12.json","type":"file","isOpen":true,"isDirectory":false,"numChildren":0,"label":"sui12.json","size":134},{"fileLocalURL":"asset/json/server/ui/sui13.json","type":"file","isOpen":true,"isDirectory":false,"numChildren":0,"label":"sui13.json","size":23276},{"fileLocalURL":"asset/json/server/ui/sui14.json","type":"file","isOpen":true,"isDirectory":false,"numChildren":0,"label":"sui14.json","size":136},{"fileLocalURL":"asset/json/server/ui/sui15.json","type":"file","isOpen":true,"isDirectory":false,"numChildren":0,"label":"sui15.json","size":732},{"fileLocalURL":"asset/json/server/ui/sui15001.json","type":"file","isOpen":true,"isDirectory":false,"numChildren":0,"label":"sui15001.json","size":5871},{"fileLocalURL":"asset/json/server/ui/sui15002.json","type":"file","isOpen":true,"isDirectory":false,"numChildren":0,"label":"sui15002.json","size":2407},{"fileLocalURL":"asset/json/server/ui/sui15003.json","type":"file","isOpen":true,"isDirectory":false,"numChildren":0,"label":"sui15003.json","size":2639},{"fileLocalURL":"asset/json/server/ui/sui15004.json","type":"file","isOpen":true,"isDirectory":false,"numChildren":0,"label":"sui15004.json","size":494},{"fileLocalURL":"asset/json/server/ui/sui16.json","type":"file","isOpen":true,"isDirectory":false,"numChildren":0,"label":"sui16.json","size":135},{"fileLocalURL":"asset/json/server/ui/sui17.json","type":"file","isOpen":true,"isDirectory":false,"numChildren":0,"label":"sui17.json","size":375},{"fileLocalURL":"asset/json/server/ui/sui18.json","type":"file","isOpen":true,"isDirectory":false,"numChildren":0,"label":"sui18.json","size":135},{"fileLocalURL":"asset/json/server/ui/sui5.json","type":"file","isOpen":true,"isDirectory":false,"numChildren":0,"label":"sui5.json","size":1644},{"fileLocalURL":"asset/json/server/ui/sui6.json","type":"file","isOpen":true,"isDirectory":false,"numChildren":0,"label":"sui6.json","size":7502},{"fileLocalURL":"asset/json/server/ui/sui7.json","type":"file","isOpen":true,"isDirectory":false,"numChildren":0,"label":"sui7.json","size":4262},{"fileLocalURL":"asset/json/server/ui/sui8.json","type":"file","isOpen":true,"isDirectory":false,"numChildren":0,"label":"sui8.json","size":3293},{"fileLocalURL":"asset/json/server/ui/sui9.json","type":"file","isOpen":true,"isDirectory":false,"numChildren":0,"label":"sui9.json","size":252},{"fileLocalURL":"asset/json/server/ui/sui19.json","type":"file","isOpen":true,"isDirectory":false,"numChildren":0,"label":"sui19.json","size":136},{"fileLocalURL":"asset/json/server/ui/sui20.json","type":"file","isOpen":true,"isDirectory":false,"numChildren":0,"label":"sui20.json","size":5583},{"fileLocalURL":"asset/json/server/ui/sui21.json","type":"file","isOpen":true,"isDirectory":false,"numChildren":0,"label":"sui21.json","size":134},{"fileLocalURL":"asset/json/server/ui/sui22.json","type":"file","isOpen":true,"isDirectory":false,"numChildren":0,"label":"sui22.json","size":134},{"fileLocalURL":"asset/json/server/ui/sui23.json","type":"file","isOpen":true,"isDirectory":false,"numChildren":0,"label":"sui23.json","size":2010},{"fileLocalURL":"asset/json/server/ui/sui24.json","type":"file","isOpen":true,"isDirectory":false,"numChildren":0,"label":"sui24.json","size":7286},{"fileLocalURL":"asset/json/server/ui/sui25.json","type":"file","isOpen":true,"isDirectory":false,"numChildren":0,"label":"sui25.json","size":2863},{"fileLocalURL":"asset/json/server/ui/sui26.json","type":"file","isOpen":true,"isDirectory":false,"numChildren":0,"label":"sui26.json","size":506},{"fileLocalURL":"asset/json/server/ui/sui27.json","type":"file","isOpen":true,"isDirectory":false,"numChildren":0,"label":"sui27.json","size":2237},{"fileLocalURL":"asset/json/server/ui/sui28.json","type":"file","isOpen":true,"isDirectory":false,"numChildren":0,"label":"sui28.json","size":121},{"fileLocalURL":"asset/json/server/variable","type":"file","isOpen":true,"isDirectory":true,"numChildren":3,"label":"variable","size":0},{"fileLocalURL":"asset/json/server/variable/string.json","type":"file","isOpen":true,"isDirectory":false,"numChildren":0,"label":"string.json","size":282},{"fileLocalURL":"asset/json/server/variable/switch.json","type":"file","isOpen":true,"isDirectory":false,"numChildren":0,"label":"switch.json","size":445},{"fileLocalURL":"asset/json/server/variable/variable.json","type":"file","isOpen":true,"isDirectory":false,"numChildren":0,"label":"variable.json","size":1324},{"fileLocalURL":"asset/json/ui","type":"file","isOpen":false,"isDirectory":true,"numChildren":2,"label":"ui","size":0},{"fileLocalURL":"asset/json/ui/data","type":"file","isOpen":true,"isDirectory":true,"numChildren":33,"label":"data","size":0},{"fileLocalURL":"asset/json/ui/data/ui1.json","type":"file","isOpen":true,"isDirectory":false,"numChildren":0,"label":"ui1.json","size":1653},{"fileLocalURL":"asset/json/ui/data/ui2.json","type":"file","isOpen":true,"isDirectory":false,"numChildren":0,"label":"ui2.json","size":5741},{"fileLocalURL":"asset/json/ui/data/ui3.json","type":"file","isOpen":true,"isDirectory":false,"numChildren":0,"label":"ui3.json","size":864},{"fileLocalURL":"asset/json/ui/data/ui4.json","type":"file","isOpen":true,"isDirectory":false,"numChildren":0,"label":"ui4.json","size":4306},{"fileLocalURL":"asset/json/ui/data/ui5.json","type":"file","isOpen":true,"isDirectory":false,"numChildren":0,"label":"ui5.json","size":17},{"fileLocalURL":"asset/json/ui/data/ui6.json","type":"file","isOpen":true,"isDirectory":false,"numChildren":0,"label":"ui6.json","size":17},{"fileLocalURL":"asset/json/ui/data/ui10.json","type":"file","isOpen":true,"isDirectory":false,"numChildren":0,"label":"ui10.json","size":4269},{"fileLocalURL":"asset/json/ui/data/ui1001.json","type":"file","isOpen":true,"isDirectory":false,"numChildren":0,"label":"ui1001.json","size":761},{"fileLocalURL":"asset/json/ui/data/ui11.json","type":"file","isOpen":true,"isDirectory":false,"numChildren":0,"label":"ui11.json","size":2658},{"fileLocalURL":"asset/json/ui/data/ui12.json","type":"file","isOpen":true,"isDirectory":false,"numChildren":0,"label":"ui12.json","size":820},{"fileLocalURL":"asset/json/ui/data/ui13.json","type":"file","isOpen":true,"isDirectory":false,"numChildren":0,"label":"ui13.json","size":29941},{"fileLocalURL":"asset/json/ui/data/ui14.json","type":"file","isOpen":true,"isDirectory":false,"numChildren":0,"label":"ui14.json","size":693},{"fileLocalURL":"asset/json/ui/data/ui15.json","type":"file","isOpen":true,"isDirectory":false,"numChildren":0,"label":"ui15.json","size":5206},{"fileLocalURL":"asset/json/ui/data/ui15001.json","type":"file","isOpen":true,"isDirectory":false,"numChildren":0,"label":"ui15001.json","size":60776},{"fileLocalURL":"asset/json/ui/data/ui15002.json","type":"file","isOpen":true,"isDirectory":false,"numChildren":0,"label":"ui15002.json","size":18076},{"fileLocalURL":"asset/json/ui/data/ui15003.json","type":"file","isOpen":true,"isDirectory":false,"numChildren":0,"label":"ui15003.json","size":19700},{"fileLocalURL":"asset/json/ui/data/ui15004.json","type":"file","isOpen":true,"isDirectory":false,"numChildren":0,"label":"ui15004.json","size":3493},{"fileLocalURL":"asset/json/ui/data/ui16.json","type":"file","isOpen":true,"isDirectory":false,"numChildren":0,"label":"ui16.json","size":819},{"fileLocalURL":"asset/json/ui/data/ui17.json","type":"file","isOpen":true,"isDirectory":false,"numChildren":0,"label":"ui17.json","size":3180},{"fileLocalURL":"asset/json/ui/data/ui18.json","type":"file","isOpen":true,"isDirectory":false,"numChildren":0,"label":"ui18.json","size":739},{"fileLocalURL":"asset/json/ui/data/ui7.json","type":"file","isOpen":true,"isDirectory":false,"numChildren":0,"label":"ui7.json","size":12238},{"fileLocalURL":"asset/json/ui/data/ui8.json","type":"file","isOpen":true,"isDirectory":false,"numChildren":0,"label":"ui8.json","size":9604},{"fileLocalURL":"asset/json/ui/data/ui9.json","type":"file","isOpen":true,"isDirectory":false,"numChildren":0,"label":"ui9.json","size":1668},{"fileLocalURL":"asset/json/ui/data/ui19.json","type":"file","isOpen":true,"isDirectory":false,"numChildren":0,"label":"ui19.json","size":1149},{"fileLocalURL":"asset/json/ui/data/ui20.json","type":"file","isOpen":true,"isDirectory":false,"numChildren":0,"label":"ui20.json","size":13007},{"fileLocalURL":"asset/json/ui/data/ui21.json","type":"file","isOpen":true,"isDirectory":false,"numChildren":0,"label":"ui21.json","size":1129},{"fileLocalURL":"asset/json/ui/data/ui22.json","type":"file","isOpen":true,"isDirectory":false,"numChildren":0,"label":"ui22.json","size":754},{"fileLocalURL":"asset/json/ui/data/ui23.json","type":"file","isOpen":true,"isDirectory":false,"numChildren":0,"label":"ui23.json","size":1284},{"fileLocalURL":"asset/json/ui/data/ui24.json","type":"file","isOpen":true,"isDirectory":false,"numChildren":0,"label":"ui24.json","size":2007},{"fileLocalURL":"asset/json/ui/data/ui25.json","type":"file","isOpen":true,"isDirectory":false,"numChildren":0,"label":"ui25.json","size":25410},{"fileLocalURL":"asset/json/ui/data/ui26.json","type":"file","isOpen":true,"isDirectory":false,"numChildren":0,"label":"ui26.json","size":1992},{"fileLocalURL":"asset/json/ui/data/ui27.json","type":"file","isOpen":true,"isDirectory":false,"numChildren":0,"label":"ui27.json","size":3709},{"fileLocalURL":"asset/json/ui/data/ui28.json","type":"file","isOpen":true,"isDirectory":false,"numChildren":0,"label":"ui28.json","size":788},{"fileLocalURL":"asset/json/ui/uiList.json","type":"file","isOpen":true,"isDirectory":false,"numChildren":0,"label":"uiList.json","size":212},{"fileLocalURL":"asset/json/variable","type":"file","isOpen":true,"isDirectory":true,"numChildren":3,"label":"variable","size":0},{"fileLocalURL":"asset/json/variable/string.json","type":"file","isOpen":true,"isDirectory":false,"numChildren":0,"label":"string.json","size":301},{"fileLocalURL":"asset/json/variable/switch.json","type":"file","isOpen":true,"isDirectory":false,"numChildren":0,"label":"switch.json","size":395},{"fileLocalURL":"asset/json/variable/variable.json","type":"file","isOpen":true,"isDirectory":false,"numChildren":0,"label":"variable.json","size":1275},{"fileLocalURL":"asset/json/standAvatar","type":"file","isOpen":true,"isDirectory":true,"numChildren":3,"label":"standAvatar","size":0},{"fileLocalURL":"asset/json/standAvatar/data","type":"file","isOpen":true,"isDirectory":true,"numChildren":4,"label":"data","size":0},{"fileLocalURL":"asset/json/standAvatar/data/standAvatar1.json","type":"file","isOpen":true,"isDirectory":false,"numChildren":0,"label":"standAvatar1.json","size":148947},{"fileLocalURL":"asset/json/standAvatar/data/standAvatar2.json","type":"file","isOpen":true,"isDirectory":false,"numChildren":0,"label":"standAvatar2.json","size":148115},{"fileLocalURL":"asset/json/standAvatar/data/standAvatar3.json","type":"file","isOpen":true,"isDirectory":false,"numChildren":0,"label":"standAvatar3.json","size":3795},{"fileLocalURL":"asset/json/standAvatar/data/standAvatar4.json","type":"file","isOpen":true,"isDirectory":false,"numChildren":0,"label":"standAvatar4.json","size":359},{"fileLocalURL":"asset/json/standAvatar/expressionList.json","type":"file","isOpen":true,"isDirectory":false,"numChildren":0,"label":"expressionList.json","size":135},{"fileLocalURL":"asset/json/standAvatar/standAvatarList.json","type":"file","isOpen":true,"isDirectory":false,"numChildren":0,"label":"standAvatarList.json","size":1452},{"fileLocalURL":"asset/_titles","type":"file","isOpen":true,"isDirectory":true,"numChildren":2,"label":"_titles","size":0},{"fileLocalURL":"asset/_titles/279542.0621852824-26706323828_0.png","type":"image/png","isOpen":true,"isDirectory":false,"numChildren":0,"label":"279542.0621852824-26706323828_0.png","size":1024962},{"fileLocalURL":"asset/_titles/180150.17067910355-80415952126_0.jpg","type":"image/jpg","isOpen":true,"isDirectory":false,"numChildren":0,"label":"180150.17067910355-80415952126_0.jpg","size":67677},{"fileLocalURL":"asset/gclife.gcdata","type":"file","isOpen":true,"isDirectory":false,"numChildren":0,"label":"gclife.gcdata","size":112}]